setup.py
Flask_Permissions.egg-info/PKG-INFO
Flask_Permissions.egg-info/SOURCES.txt
Flask_Permissions.egg-info/dependency_links.txt
Flask_Permissions.egg-info/not-zip-safe
Flask_Permissions.egg-info/requires.txt
Flask_Permissions.egg-info/top_level.txt
flask_permissions/__init__.py
flask_permissions/core.py
flask_permissions/decorators.py
flask_permissions/models.py
flask_permissions/tests.py
flask_permissions/utils.py