Metadata-Version: 1.0
Name: Flask-Permissions
Version: 0.1.18
Summary: Simple user permissions for Flask
Home-page: https://github.com/raddevon/flask-permissions
Author: Devon Campbell
Author-email: devon@raddevon.com
License: BSD
Platform: any
Classifier: Environment :: Web Environment
Classifier: Intended Audience :: Developers
Classifier: License :: OSI Approved :: BSD License
Classifier: Operating System :: OS Independent
Classifier: Programming Language :: Python
Classifier: Topic :: Internet :: WWW/HTTP :: Dynamic Content
Classifier: Topic :: Software Development :: Libraries :: Python Modules
